piney_event/event.py
piney_event-0.0.1.dist-info/LICENSE
piney_event-0.0.1.dist-info/METADATA
piney_event-0.0.1.dist-info/WHEEL
piney_event-0.0.1.dist-info/top_level.txt
piney_event-0.0.1.dist-info/RECORD
