Metadata-Version: 2.1
Name: piney_event
Version: 0.0.1
Summary: A tiny Event System for Python
Author-email: Sahar Shulman <dillpickledev@gmail.com>
Project-URL: Homepage, https://github.com/hohfchns/piney_event
Project-URL: Issues, https://github.com/hohfchns/piney_event/issues
Classifier: Programming Language :: Python :: 3
Classifier: License :: OSI Approved :: BSD License
Classifier: Operating System :: OS Independent
Requires-Python: >=3.11
License-File: LICENSE
